xray/__init__.py
xray/lsp_config.json
xray/mcp_server.py
xray/core/__init__.py
xray/core/indexer.py
git_project_xray_mcp-0.2.4.dist-info/METADATA
git_project_xray_mcp-0.2.4.dist-info/WHEEL
git_project_xray_mcp-0.2.4.dist-info/entry_points.txt
git_project_xray_mcp-0.2.4.dist-info/licenses/LICENSE
git_project_xray_mcp-0.2.4.dist-info/RECORD
