Metadata-Version: 2.4
Name: git-project-xray-mcp
Version: 0.2.4
Summary: XRAY: Progressive code intelligence for AI assistants - Map, Find, Impact
Project-URL: Homepage, https://github.com/Jamie-BitFlight/git-project-xray-mcp
Project-URL: Repository, https://github.com/Jamie-BitFlight/git-project-xray-mcp
Project-URL: Issues, https://github.com/Jamie-BitFlight/git-project-xray-mcp/issues
Author-email: Srijan Shukla <srijanshukla18@gmail.com>
License: MIT
License-File: LICENSE
Keywords: ai-assistant,ast-grep,code-analysis,code-intelligence,mcp,structural-search
Classifier: Development Status :: 4 - Beta
Classifier: Intended Audience :: Developers
Classifier: License :: OSI Approved :: MIT License
Classifier: Programming Language :: Python :: 3
Classifier: Programming Language :: Python :: 3.10
Classifier: Programming Language :: Python :: 3.11
Classifier: Programming Language :: Python :: 3.12
Requires-Python: >=3.10
Requires-Dist: ast-grep-cli>=0.39.0
Requires-Dist: fastmcp>=0.1.0
Requires-Dist: thefuzz>=0.20.0
